<?xml version="1.0" encoding="UTF-8"?>
<WindbotSettings>
    <Healer>
        <SpellHealer enabled="yes">
            <HealRule name="Exura Ico" spell="Light Healing" condition="Health Percent below" conditionMin="50" conditionMax="60" extraCondition="No Extra Condition" extraConditionMin="0" extraConditionMax="0" enabled="yes" spamMin="200" spamMax="500" triggerKey="&lt;no key&gt;" dontOverrideActions="no"/>
        </SpellHealer>
        <PotionHealer enabled="yes">
            <HealRule name="Health Potion" spell="Health Potion" condition="Health Percent below" conditionMin="30" conditionMax="50" extraCondition="No Extra Condition" extraConditionMin="0" extraConditionMax="0" enabled="no" spamMin="200" spamMax="500" triggerKey="&lt;no key&gt;" dontOverrideActions="no"/>
            <HealRule name="Mana Potion" spell="Mana Potion" condition="Mana Percent below" conditionMin="10" conditionMax="20" extraCondition="No Extra Condition" extraConditionMin="0" extraConditionMax="0" enabled="yes" spamMin="200" spamMax="500" triggerKey="&lt;no key&gt;" dontOverrideActions="no"/>
        </PotionHealer>
        <ConditionHealer enabled="no"/>
        <ManaTrainer manaTrainCondition="Mana Percent above" manaTrainMin="90" manaTrainMax="96" enabled="yes">
            <HealRule name="Waste" spell="Light Healing" extraCondition="No Extra Condition" extraConditionMin="0" extraConditionMax="0" enabled="yes" spamMin="200" spamMax="500" triggerKey="&lt;no key&gt;" dontOverrideActions="no"/>
        </ManaTrainer>
    </Healer>
    <Scripter>
        <HotkeyScripts>
            <HotkeyScript name="showbot" script="showbot()" triggerKey="Shift + F11" hotkeyTriggerMode="0"/>
            <HotkeyScript name="PauseHotkey" script="if not $cavebot or not $targeting then&#13;&#10;    listas('Enabling Cavebot and Targeting')&#13;&#10;    setcavebot('on')&#13;&#10;    settargeting('on')&#13;&#10;    wait(1000)&#13;&#10;else&#13;&#10;    listas('Disabling Cavebot and Targeting')&#13;&#10;    setcavebot('off')&#13;&#10;    settargeting('off')&#13;&#10;    stopattack()&#13;&#10;    wait(1000)&#13;&#10;end" triggerKey="Pause" hotkeyTriggerMode="0"/>
        </HotkeyScripts>
        <PersistentScripts>
            <PersistentScript name="backpack" script="auto(5000)&#10;setlootingdestination(&quot;mainbp&quot;, getuseroption(&quot;MainBP&quot;))&#10;setlootingdestination(&quot;goldbp&quot;, getuseroption(&quot;GoldBP&quot;))&#10;setlootingdestination(&quot;suppbp&quot;, getuseroption(&quot;SuppBP&quot;))&#10;setlootingdestination(&quot;lootbp&quot;, getuseroption(&quot;LootBP&quot;))&#10;setlootingdestination(&quot;maindpbp&quot;, getuseroption(&quot;MainDPBP&quot;))&#10;setlootingdestination(&quot;stackdpbp&quot;, getuseroption(&quot;StackBP&quot;))&#10;setlootingdestination(&quot;lootdpbp&quot;, getuseroption(&quot;RareBP&quot;))&#10;setlootingdestination(&quot;supplybp&quot;, getuseroption(&quot;SupplyBP&quot;))" enabled="yes"/>
            <PersistentScript name="vial" script="--Dont edit here--[www.Lucksstore.com]&#10;auto(100) listas(&quot;dontlist&quot;)&#10;if itemcount(284) and itemcount(283) and itemcount(285) and $cap &lt;= 120 and maround() &lt;= 0 &#10;then dropitems(284,283,285)&#10;end" enabled="no"/>
            <PersistentScript name="safe bank" script="auto(700)&#10;&#10;&#10;foreach newmessage m do&#10;&#9;if m.content == &quot;There is not enough gold on your account.&quot; and m.type == 6 then&#10;&#9;&#9;logout()&#10;&#9;end&#10;end" enabled="yes"/>
            <PersistentScript name="AttackCreature" script="auto(1000)&#10;&#10;foreach creature m &quot;ms&quot; do&#10;&#9;if $standtime &gt; 9000 and (not $targeting) then&#10;&#9;&#9;if m.dist &lt;= 1 and (not m.iswalking) and m.isreachable and m.walkblock then&#10;&#9;&#9;&#9;attack(m.id)&#10;&#9;&#9;&#9;break&#10;&#9;&#9;end&#10;&#9;end&#10;end&#10;" enabled="yes"/>
            <PersistentScript name="Supp" script="MPname = getuseroption('MPname')&#10;MPtobuy = getuseroption('MpToBuy')&#10;MPprice = getuseroption('MPprice')&#10;MPtoback = getuseroption('MpToLeave')&#10;&#10;HPname = getuseroption('HPname')&#10;HPtobuy = getuseroption('HpToBuy')&#10;HPprice = getuseroption('HPprice')&#10;HPtoback = getuseroption('HpToLeave')&#10;&#10;Captoback = getuseroption('CapToLeave')&#10;&#10;&#10;&#10;&#10;" enabled="yes"/>
        </PersistentScripts>
    </Scripter>
    <HUDs>
        <HUDScripts>
            <HUDScript name="MonitorMyHunting" script="init start&#13;&#10;&#9;--&#13;&#10;&#9;--                        88                                                                  &#13;&#10;&#9;--                        &quot;&quot;                                                ,d                &#13;&#10;&#9;--                                                                          88                &#13;&#10;&#9;--             ,adPPYba,  88  8b,dPPYba,  88,dPYba,,adPYba,   ,adPPYYba,  MM88MMM  ,adPPYba,  &#13;&#10;&#9;--             I8[    &quot;&quot;  88  88P'   &quot;Y8  88P'   &quot;88&quot;    &quot;8a  &quot;&quot;     `Y8    88    a8P_____88  &#13;&#10;&#9;--              `&quot;Y8ba,   88  88          88      88      88  ,adPPPPP88    88    8PP&quot;&quot;&quot;&quot;&quot;&quot;&quot;  &#13;&#10;&#9;--             aa    ]8I  88  88          88      88      88  88,    ,88    88,   &quot;8b,   ,aa  &#13;&#10;&#9;--   Author:   `&quot;YbbdP&quot;'  88  88          88      88      88  `&quot;8bbdP&quot;Y8    &quot;Y888  `&quot;Ybbd8&quot;'  &#13;&#10;&#9;--   &#13;&#10;&#9;--   Monitor My Hunting!&#13;&#10;&#9;--&#13;&#10;&#9;--   Version: 1.0&#13;&#10;&#9;--   Created: 29.12.2013&#13;&#10;&#9;--   Last update: 29.12.2013&#13;&#10;&#9;--&#13;&#10;&#13;&#10;&#9;local MMH = {&#13;&#10;&#9;&#9;SHOW_ALL_ITEMS = false,&#13;&#10;&#9;&#9;SHOW_ALL_SUPPLIES = false,&#13;&#10;&#9;}&#13;&#10;&#13;&#10;&#9;-- [[ Do not change anything below this line. ]] --&#13;&#10;&#13;&#10;&#9;-- [[ COLORS ]] --&#13;&#10;&#9;MMH.COLORS = {}&#13;&#10;&#9;MMH.COLORS.FONT_COLOR = color(255, 255, 255, 0)&#13;&#10;&#9;MMH.COLORS.SECTION_HEADER_BACKGROUND = {0.0, color(36, 68, 105, 20), 0.23, color(39, 73, 114, 20), 0.76, color(21, 39, 60, 20)}&#13;&#10;&#9;MMH.COLORS.ENTRY_NAME_BACKGROUND = {0.0, color(75, 75, 75, 20), 0.23, color(45, 45, 45, 20), 0.76, color(19, 19, 19, 20)}&#13;&#10;&#9;MMH.COLORS.ENTRY_VALUE_BACKGROUND = {0.0, color(145, 95, 0, 20), 0.23, color(158, 104, 0, 20), 0.76, color(84, 55, 0, 20)}&#13;&#10;&#9;MMH.COLORS.RESULT_POSITIVE_BACKGROUND = {0.0, color(65, 96, 12, 20), 0.23, color(67, 99, 13, 20), 0.76, color(36, 52, 6, 20)}&#13;&#10;&#9;MMH.COLORS.RESULT_NEGATIVE_BACKGROUND = {0.0, color(90, 12, 15, 20), 0.23, color(98, 13, 17, 20), 0.76, color(52, 6, 9, 20)}&#13;&#10;&#9;MMH.COLORS.RESET_BUTTON_BACKGROUND = MMH.COLORS.RESULT_POSITIVE_BACKGROUND&#13;&#10;&#13;&#10;&#9;-- [[ ELEMENTS ]] --&#13;&#10;&#9;MMH.ELEMENTS = {}&#13;&#10;&#9;MMH.ELEMENTS.RESET_BUTTON = -1&#13;&#10;&#9;MMH.ELEMENTS.SWITCH_ITEMS_LOOTED = -1&#13;&#10;&#9;MMH.ELEMENTS.SWITCH_SUPPLIES_USED = -1&#13;&#10;&#13;&#10;&#9;-- [[ SECTION STATES ]] --&#13;&#10;&#9;MMH.SECTIONS = {}&#13;&#10;&#9;MMH.SECTIONS.ITEMS_LOOTED = true&#13;&#10;&#9;MMH.SECTIONS.SUPPLIES_USED = true&#13;&#10;&#13;&#10;&#9;-- [[ OTHERS ]] --&#9;&#13;&#10;&#9;filterinput(false, true, false, false)&#13;&#10;&#13;&#10;&#9;local MOVING, TEMP, MOVED = false, {0, 0}, {0, 0}&#13;&#10;&#13;&#10;&#9;function inputevents(e)&#13;&#10;&#9;&#9;if (e.type == IEVENT_LMOUSEDOWN) then&#13;&#10;&#9;&#9;&#9;if (e.elementid == MMH.ELEMENTS.RESET_BUTTON) then&#13;&#10;&#9;&#9;&#9;&#9;resetcharactertime()&#13;&#10;&#9;&#9;&#9;&#9;resetlootcounter()&#13;&#10;&#9;&#9;&#9;&#9;resetexpcounter()&#13;&#10;&#9;&#9;&#9;elseif (e.elementid == MMH.ELEMENTS.SWITCH_ITEMS_LOOTED) then&#13;&#10;&#9;&#9;&#9;&#9;MMH.SECTIONS.ITEMS_LOOTED = not MMH.SECTIONS.ITEMS_LOOTED&#13;&#10;&#9;&#9;&#9;elseif (e.elementid == MMH.ELEMENTS.SWITCH_SUPPLIES_USED) then&#13;&#10;&#9;&#9;&#9;&#9;MMH.SECTIONS.SUPPLIES_USED = not MMH.SECTIONS.SUPPLIES_USED&#13;&#10;&#9;&#9;&#9;end&#13;&#10;&#9;&#9;end&#13;&#10;&#13;&#10;&#9;&#9;if (e.type == IEVENT_MMOUSEDOWN) then&#13;&#10;&#9;&#9;&#9;MOVING, TEMP = true, {$cursor.x - MOVED[1], $cursor.y - MOVED[2]}&#13;&#10;&#9;&#9;end&#13;&#10;&#13;&#10;&#9;&#9;if (e.type == IEVENT_MMOUSEUP) then&#13;&#10;&#9;&#9;&#9;MOVING = false&#13;&#10;&#9;&#9;end&#13;&#10;&#9;end&#13;&#10;&#13;&#10;&#9;setmaskcolorxp(0)&#13;&#10;init end&#13;&#10;&#13;&#10;if (MOVING) then&#13;&#10;    auto(10)&#13;&#10;    MOVED = {$cursor.x - TEMP[1], $cursor.y - TEMP[2]}&#13;&#10;end&#13;&#10;&#13;&#10;setposition($clientwin.right - 424 + MOVED[1], $worldwin.top + MOVED[2])&#13;&#10;setfontstyle('Tahoma', 8, 75, MMH.COLORS.FONT_COLOR, 1, color(0, 0, 0, 20))&#13;&#10;&#13;&#10;local ROW_QUANTITY, STRING_WIDTH, STRING_HEIGHT = 0, measurestring('TEMP')&#13;&#10;local ITEMS_LOOTED_WORTH, ITEM_LOOTED_QUANTITY, ITEM_LOOTED_WORTH = 0, 0, 0&#13;&#10;local SUPPLIES_USED_WORTH, SUPPLY_USED_QUANTITY, SUPPLY_USED_WORTH = 0, 0, 0&#13;&#10;&#13;&#10;setfillstyle('gradient', 'linear', 2, 0, 0, 0, 21)&#13;&#10;addgradcolors(unpack(MMH.COLORS.ENTRY_NAME_BACKGROUND))&#13;&#10;drawroundrect(0, 0, 240, 20, 2, 2)&#13;&#10;drawtext('Monitor My Hunting v1.0', 6, 20 / 2 - STRING_HEIGHT * 0.5)&#13;&#10;&#13;&#10;setfillstyle('gradient', 'linear', 2, 0, 0, 0, 21)&#13;&#10;addgradcolors(unpack(MMH.COLORS.RESET_BUTTON_BACKGROUND))&#13;&#10;MMH.ELEMENTS.RESET_BUTTON = drawroundrect(196, 0, 44, 20, 2, 2)&#13;&#10;drawtext('RESET', 202, 20 / 2 - STRING_HEIGHT * 0.5)&#13;&#10;&#13;&#10;setfontsize(7)&#13;&#10;&#13;&#10;STRING_WIDTH, STRING_HEIGHT = measurestring('TEMP')&#13;&#10;&#13;&#10;setfillstyle('gradient', 'linear', 2, 0, 0, 0, 16)&#13;&#10;addgradcolors(unpack(MMH.COLORS.ENTRY_NAME_BACKGROUND))&#13;&#10;drawroundrect(0, 23, 240, 15, 2, 2)&#13;&#10;drawtext('Looting Accuracy', 6, 23 + 15 / 2 - STRING_HEIGHT * 0.5 + 1)&#13;&#10;&#13;&#10;setfillstyle('gradient', 'linear', 2, 0, 0, 0, 16)&#13;&#10;addgradcolors(unpack(MMH.COLORS.ENTRY_VALUE_BACKGROUND))&#13;&#10;drawroundrect(130, 23, 110, 15, 2, 2)&#13;&#10;drawtext(string.format('%.2f', $lootaccuracy) .. '%', 136, 23 + 15 / 2 - STRING_HEIGHT * 0.5 + 1)&#13;&#10;&#13;&#10;setfontsize(8)&#13;&#10;&#13;&#10;STRING_WIDTH, STRING_HEIGHT = measurestring('TEMP')&#13;&#10;&#13;&#10;setfillstyle('gradient', 'linear', 2, 0, 0, 0, 21)&#13;&#10;addgradcolors(unpack(MMH.COLORS.SECTION_HEADER_BACKGROUND))&#13;&#10;drawroundrect(0, 41, 240, 20, 2, 2)&#13;&#10;drawtext('ITEMS LOOTED', 6, 41 + 20 / 2 - STRING_HEIGHT * 0.5)&#13;&#10;&#13;&#10;setfillstyle('gradient', 'linear', 2, 0, 0, 0, 21)&#13;&#10;if (MMH.SECTIONS.ITEMS_LOOTED) then&#13;&#10;&#9;addgradcolors(unpack(MMH.COLORS.RESULT_POSITIVE_BACKGROUND))&#13;&#10;else&#13;&#10;&#9;addgradcolors(unpack(MMH.COLORS.RESULT_NEGATIVE_BACKGROUND))&#13;&#10;end&#13;&#10;MMH.ELEMENTS.SWITCH_ITEMS_LOOTED = drawroundrect(220, 41, 20, 20, 2, 2)&#13;&#10;drawtext('X', 228, 41 + 20 / 2 - STRING_HEIGHT * 0.5)&#13;&#10;&#13;&#10;setfontsize(7)&#13;&#10;&#13;&#10;STRING_WIDTH, STRING_HEIGHT = measurestring('TEMP')&#13;&#10;&#13;&#10;foreach lootingitem ItemEntry do&#13;&#10;&#9;if (MMH.SHOW_ALL_ITEMS or ItemEntry.amountlooted &gt; 0) then&#13;&#10;&#9;&#9;ITEM_LOOTED_QUANTITY = ItemEntry.amountlooted&#13;&#10;&#9;&#9;ITEM_LOOTED_WORTH = ItemEntry.sellprice * ITEM_LOOTED_QUANTITY&#13;&#10;&#13;&#10;&#9;&#9;if (MMH.SECTIONS.ITEMS_LOOTED) then&#13;&#10;&#9;&#9;&#9;setfillstyle('gradient', 'linear', 2, 0, 0, 0, 16)&#13;&#10;&#9;&#9;&#9;addgradcolors(unpack(MMH.COLORS.ENTRY_NAME_BACKGROUND))&#13;&#10;&#9;&#9;&#9;drawroundrect(0, 64 + ROW_QUANTITY * 18, 240, 15, 2, 2)&#13;&#10;&#9;&#9;&#13;&#10;&#9;&#9;&#9;setcompositionmode(CompositionMode_SourceOver)&#13;&#10;&#9;&#9;&#9;drawitem(ItemEntry.id, 6, 64 + ROW_QUANTITY * 18, 50, 100)&#13;&#10;&#9;&#9;&#9;setcompositionmode(CompositionMode_Automatic)&#13;&#10;&#13;&#10;&#9;&#9;&#9;drawtext(((#ItemEntry.name &gt; 16 and string.match(string.sub(ItemEntry.name, 1, 16), '(.-)%s?$') .. '...') or ItemEntry.name):capitalizeall(), 28, 64 + ROW_QUANTITY * 18 + 15 / 2 - STRING_HEIGHT * 0.5)&#13;&#10;&#13;&#10;&#9;&#9;&#9;setfillstyle('gradient', 'linear', 2, 0, 0, 0, 16)&#13;&#10;&#9;&#9;&#9;addgradcolors(unpack(MMH.COLORS.ENTRY_VALUE_BACKGROUND))&#13;&#10;&#9;&#9;&#9;drawroundrect(130, 64 + ROW_QUANTITY * 18, 110, 15, 2, 2)&#13;&#10;&#9;&#9;&#9;drawtext(num(ITEM_LOOTED_QUANTITY) .. ' (' .. math.floor(ITEM_LOOTED_WORTH / 100) / 10 .. 'K)', 136, 64 + ROW_QUANTITY * 18 + 15 / 2 - STRING_HEIGHT * 0.5)&#13;&#10;&#13;&#10;&#9;&#9;&#9;ROW_QUANTITY = ROW_QUANTITY + 1&#13;&#10;&#9;&#9;end&#13;&#10;&#13;&#10;&#9;&#9;ITEMS_LOOTED_WORTH = ITEMS_LOOTED_WORTH + ITEM_LOOTED_WORTH&#13;&#10;&#9;end&#13;&#10;end&#13;&#10;&#13;&#10;setfillstyle('gradient', 'linear', 2, 0, 0, 0, 16)&#13;&#10;addgradcolors(unpack(MMH.COLORS.ENTRY_NAME_BACKGROUND))&#13;&#10;drawroundrect(0, 64 + ROW_QUANTITY * 18, 240, 15, 2, 2)&#13;&#10;drawtext('Total: ' .. num(ITEMS_LOOTED_WORTH) .. ' GPs', 6, 64 + ROW_QUANTITY * 18 + 15 / 2 - STRING_HEIGHT * 0.5)&#13;&#10;&#13;&#10;ROW_QUANTITY = ROW_QUANTITY + 1&#13;&#10;&#13;&#10;setfontsize(8)&#13;&#10;&#13;&#10;STRING_WIDTH, STRING_HEIGHT = measurestring('TEMP')&#13;&#10;&#13;&#10;setfillstyle('gradient', 'linear', 2, 0, 0, 0, 21)&#13;&#10;addgradcolors(unpack(MMH.COLORS.SECTION_HEADER_BACKGROUND))&#13;&#10;drawroundrect(0, 64 + ROW_QUANTITY * 18, 240, 20, 2, 2)&#13;&#10;drawtext('SUPPLIES USED', 6, 64 + ROW_QUANTITY * 18 + 20 / 2 - STRING_HEIGHT * 0.5)&#13;&#10;&#13;&#10;setfillstyle('gradient', 'linear', 2, 0, 0, 0, 21)&#13;&#10;if (MMH.SECTIONS.SUPPLIES_USED) then&#13;&#10;&#9;addgradcolors(unpack(MMH.COLORS.RESULT_POSITIVE_BACKGROUND))&#13;&#10;else&#13;&#10;&#9;addgradcolors(unpack(MMH.COLORS.RESULT_NEGATIVE_BACKGROUND))&#13;&#10;end&#13;&#10;MMH.ELEMENTS.SWITCH_SUPPLIES_USED = drawroundrect(220, 64 + ROW_QUANTITY * 18, 20, 20, 2, 2)&#13;&#10;drawtext('X', 228, 64 + ROW_QUANTITY * 18 + 20 / 2 - STRING_HEIGHT * 0.5)&#13;&#10;&#13;&#10;setfontsize(7)&#13;&#10;&#13;&#10;STRING_WIDTH, STRING_HEIGHT = measurestring('TEMP')&#13;&#10;&#13;&#10;foreach supplyitem ItemEntry do&#13;&#10;&#9;if (MMH.SHOW_ALL_SUPPLIES or ItemEntry.amountused &gt; 0) then&#13;&#10;&#9;&#9;SUPPLY_USED_QUANTITY = ItemEntry.amountused&#13;&#10;&#9;&#9;SUPPLY_USED_WORTH = ItemEntry.buyprice * SUPPLY_USED_QUANTITY&#13;&#10;&#13;&#10;&#9;&#9;if (MMH.SECTIONS.SUPPLIES_USED) then&#13;&#10;&#9;&#9;&#9;setfillstyle('gradient', 'linear', 2, 0, 0, 0, 16)&#13;&#10;&#9;&#9;&#9;addgradcolors(unpack(MMH.COLORS.ENTRY_NAME_BACKGROUND))&#13;&#10;&#9;&#9;&#9;drawroundrect(0, 87 + ROW_QUANTITY * 18, 240, 15, 2, 2)&#13;&#10;&#13;&#10;&#9;&#9;&#9;setcompositionmode(CompositionMode_SourceOver)&#13;&#10;&#9;&#9;&#9;drawitem(ItemEntry.id, 6, 87 + ROW_QUANTITY * 18, 50, 100)&#13;&#10;&#9;&#9;&#9;setcompositionmode(CompositionMode_Automatic)&#13;&#10;&#13;&#10;&#9;&#9;&#9;drawtext(((#ItemEntry.name &gt; 16 and string.match(string.sub(ItemEntry.name, 1, 16), '(.-)%s?$') .. '...') or ItemEntry.name):capitalizeall(), 28, 87 + ROW_QUANTITY * 18 + 15 / 2 - STRING_HEIGHT * 0.5)&#13;&#10;&#13;&#10;&#9;&#9;&#9;setfillstyle('gradient', 'linear', 2, 0, 0, 0, 16)&#13;&#10;&#9;&#9;&#9;addgradcolors(unpack(MMH.COLORS.ENTRY_VALUE_BACKGROUND))&#13;&#10;&#9;&#9;&#9;drawroundrect(130, 87 + ROW_QUANTITY * 18, 110, 15, 2, 2)&#13;&#10;&#9;&#9;&#9;drawtext(num(SUPPLY_USED_QUANTITY) .. ' (' .. math.floor(SUPPLY_USED_WORTH / 100) / 10 .. 'K)', 136, 87 + ROW_QUANTITY * 18 + 15 / 2 - STRING_HEIGHT * 0.5)&#13;&#10;&#13;&#10;&#9;&#9;&#9;ROW_QUANTITY = ROW_QUANTITY + 1&#13;&#10;&#9;&#9;end&#13;&#10;&#13;&#10;&#9;&#9;SUPPLIES_USED_WORTH = SUPPLIES_USED_WORTH + SUPPLY_USED_WORTH&#13;&#10;&#9;end&#13;&#10;end&#13;&#10;&#13;&#10;if (MMH.SECTIONS.SUPPLIES_USED) then&#13;&#10;&#9;setfillstyle('gradient', 'linear', 2, 0, 0, 0, 16)&#13;&#10;&#9;addgradcolors(unpack(MMH.COLORS.ENTRY_NAME_BACKGROUND))&#13;&#10;&#9;drawroundrect(0, 87 + ROW_QUANTITY * 18, 240, 15, 2, 2)&#13;&#10;&#13;&#10;&#9;setcompositionmode(CompositionMode_SourceOver)&#13;&#10;&#9;drawitem(3031, 6, 87 + ROW_QUANTITY * 18, 50, 100)&#13;&#10;&#9;setcompositionmode(CompositionMode_Automatic)&#13;&#10;&#13;&#10;&#9;drawtext('Money Spent', 28, 87 + ROW_QUANTITY * 18 + 15 / 2 - STRING_HEIGHT * 0.5)&#13;&#10;&#13;&#10;&#9;setfillstyle('gradient', 'linear', 2, 0, 0, 0, 16)&#13;&#10;&#9;addgradcolors(unpack(MMH.COLORS.ENTRY_VALUE_BACKGROUND))&#13;&#10;&#9;drawroundrect(130, 87 + ROW_QUANTITY * 18, 110, 15, 2, 2)&#13;&#10;&#9;drawtext(num($moneyspent) .. ' (' .. math.floor($moneyspent / 100) / 10 .. 'K)', 136, 87 + ROW_QUANTITY * 18 + 15 / 2 - STRING_HEIGHT * 0.5)&#13;&#10;&#13;&#10;&#9;ROW_QUANTITY = ROW_QUANTITY + 1&#13;&#10;end&#13;&#10;&#13;&#10;SUPPLIES_USED_WORTH = SUPPLIES_USED_WORTH + $moneyspent&#13;&#10;&#13;&#10;setfillstyle('gradient', 'linear', 2, 0, 0, 0, 16)&#13;&#10;addgradcolors(unpack(MMH.COLORS.ENTRY_NAME_BACKGROUND))&#13;&#10;drawroundrect(0, 87 + ROW_QUANTITY * 18, 240, 15, 2, 2)&#13;&#10;drawtext('Total: ' .. num(SUPPLIES_USED_WORTH) .. ' GPs', 6, 87 + ROW_QUANTITY * 18 + 15 / 2 - STRING_HEIGHT * 0.5)&#13;&#10;&#13;&#10;ROW_QUANTITY = ROW_QUANTITY + 1&#13;&#10;&#13;&#10;setfontsize(8)&#13;&#10;&#13;&#10;STRING_WIDTH, STRING_HEIGHT = measurestring('TEMP')&#13;&#10;&#13;&#10;setfillstyle('gradient', 'linear', 2, 0, 0, 0, 21)&#13;&#10;if (ITEMS_LOOTED_WORTH &gt;= SUPPLIES_USED_WORTH) then&#13;&#10;&#9;addgradcolors(unpack(MMH.COLORS.RESULT_POSITIVE_BACKGROUND))&#13;&#10;else&#13;&#10;&#9;addgradcolors(unpack(MMH.COLORS.RESULT_NEGATIVE_BACKGROUND))&#13;&#10;end&#13;&#10;drawroundrect(0, 87 + ROW_QUANTITY * 18, 240, 20, 2, 2)&#13;&#10;drawtext(((ITEMS_LOOTED_WORTH &gt;= SUPPLIES_USED_WORTH and ('PROFIT: ')) or ('WASTE: ')) .. num(ITEMS_LOOTED_WORTH - SUPPLIES_USED_WORTH) .. ' GPs (' .. math.abs(math.floor(((ITEMS_LOOTED_WORTH - SUPPLIES_USED_WORTH) * 3600) / ($charactertime / 1000) / 100) / 10) .. ' k/h)', 6, 87 + ROW_QUANTITY * 18 + 20 / 2 - STRING_HEIGHT * 0.5)" enabled="yes" refreshRate="100"/>
            <HUDScript name="MonitorMyStats" script="init start&#10;    --&#10;    --              88                                                                  &#10;    --              &quot;&quot;                                                ,d                &#10;    --                                                                88                &#10;    --   ,adPPYba,  88  8b,dPPYba,  88,dPYba,,adPYba,   ,adPPYYba,  MM88MMM  ,adPPYba,  &#10;    --   I8[    &quot;&quot;  88  88P'   &quot;Y8  88P'   &quot;88&quot;    &quot;8a  &quot;&quot;     `Y8    88    a8P_____88  &#10;    --    `&quot;Y8ba,   88  88          88      88      88  ,adPPPPP88    88    8PP&quot;&quot;&quot;&quot;&quot;&quot;&quot;  &#10;    --   aa    ]8I  88  88          88      88      88  88,    ,88    88,   &quot;8b,   ,aa  &#10;    --   `&quot;YbbdP&quot;'  88  88          88      88      88  `&quot;8bbdP&quot;Y8    &quot;Y888  `&quot;Ybbd8&quot;'  &#10;    --&#10;&#10;    --   Name: Monitor My Stats&#10;    --   Last Updated: 19/12/2013&#10;    --   Version: 1.0&#10;&#10;    local MMS = {&#10;        ShowInfo = false,&#10;&#10;        Title = &quot;SCRIPT INFO&quot;,&#10;        Creator = &quot;CREATOR NAME&quot;,&#10;        Info = 'Voc - Script Name',&#10;        Version = '1.0.0'&#10;    }&#10;&#10;    -- [[ Do not change anything below this line. ]] --&#10;&#10;    filterinput(false, true, false, false)&#10;&#10;    local HUD_Sections = {&#10;        {Name = 'OTHERS', State = true, Items = {&#10;                {'Ping', function() return $ping .. ' (avg: ' .. $pingaverage .. ')' end},&#10;                {'Bank Balance', function() return num($balance) end},&#10;            }&#10;        },&#10;&#10;        {Name = 'CHARACTER STATS', State = true, Items = {&#10;                {'Level', function() return $level .. ' (' .. 100 - math.floor(($exp - expatlvl($level)) * 100 / (expatlvl($level + 1) - expatlvl($level))) .. '%)' end},&#10;                {'Experience', function() return num($exp) end},&#10;                {'Magic Level', function() return $mlevel .. ' (' .. 100 - $mlevelpc .. '%)' end},&#10;                {'Weapon Skill', function() local _ = WeaponSkill() return _.skill .. ' (' .. 100 - _.skillpc .. '%)' end},&#10;                {'Shielding', function() return $shielding .. ' (' .. 100 - $shieldingpc .. '%)' end},&#10;                {'Fishing', function() return $fishing .. ' (' .. 100 - $fishingpc .. '%)' end}&#10;            }&#10;        },&#10;&#10;        {Name = 'ENGINE STATES', State = true, Items = {&#10;                {'Spell Healer', function() return getsetting('SpellHealer/Enabled') end, function() return toggle('SpellHealer/Enabled') end},&#10;                {'Potion Healer', function() return getsetting('PotionHealer/Enabled') end, function() return toggle('PotionHealer/Enabled') end},&#10;                {'Condition Healer', function() return getsetting('ConditionHealer/Enabled') end, function() return toggle('ConditionHealer/Enabled') end},&#10;                {'Mana Training', function() return getsetting('ManaTrainer/Enabled') end, function() return toggle('ManaTrainer/Enabled') end},&#10;                {'Cavebot', function() return getsetting('Cavebot/Enabled') end, function() return toggle('Cavebot/Enabled') end},&#10;                {'Looting', function() return getsetting('Looting/Enabled') end, function() return toggle('Looting/Enabled') end},&#10;                {'Targeting', function() return getsetting('Targeting/Enabled') end, function() return toggle('Targeting/Enabled') end}&#10;            }&#10;        },&#10;&#10;        {Name = 'BOTTING STATS', State = true, Items = {&#10;                {'Experience per Hour', function() return num($exphour) end},&#10;                {'Experience Left', function() return num(exptolevel()) end},&#10;                {'Experience Today', function() return num($expgained) end},&#10;                {'Time to Next Level', function() return time(timetolevel()) end},&#10;                {'Played Time', function() return time(math.floor($charactertime / 1000)) end},&#10;                {'Stamina', function() return time($stamina) end}&#10;            }&#10;        }&#10;    }&#10;&#10;    local HUD_Colors = {&#10;            Font = color(255, 255, 255, 0),&#10;            SectionHeaderBackground = {0.0, color(36, 68, 105, 20), 0.23, color(39, 73, 114, 20), 0.76, color(21, 39, 60, 20)},&#10;            EntryNameBackground = {0.0, color(75, 75, 75, 20), 0.23, color(45, 45, 45, 20), 0.76, color(19, 19, 19, 20)},&#10;            EntryValueBackground = {0.0, color(145, 95, 0, 20), 0.23, color(158, 104, 0, 20), 0.76, color(84, 55, 0, 20)},&#10;            EntryValueEnabledBackground = {0.0, color(65, 96, 12, 20), 0.23, color(67, 99, 13, 20), 0.76, color(36, 52, 6, 20)},&#10;            EntryValueDisabledBackground = {0.0, color(90, 12, 15, 20), 0.23, color(98, 13, 17, 20), 0.76, color(52, 6, 9, 20)},&#10;    }&#10;&#10;    function WeaponSkill()&#10;        local SkillTypes = {&#10;            ['axe'] = {type = 'axe', skill = $axe, skillpc = $axepc},&#10;            ['club'] = {type = 'club', skill = $club, skillpc = $clubpc},&#10;            ['sword'] = {type = 'sword', skill = $sword, skillpc = $swordpc},&#10;            ['bow'] = {type = 'distance', skill = $distance, skillpc = $distancepc},&#10;            ['distance weapon'] = {type = 'distance', skill = $distance, skillpc = $distancepc},&#10;            ['no weapon'] = {type = 'fist', skill = $fist, skillpc = $fistpc},&#10;            ['rod'] = {type = 'magic', skill = $mlevel, skillpc = $mlevelpc},&#10;            ['wand'] = {type = 'magic', skill = $mlevel, skillpc = $mlevelpc},&#10;        }&#10;&#10;        return SkillTypes[findweapontype()]&#10;    end&#10;&#10;    local Moving, Temp, Moved = false, {0, 0}, {0, 0}&#10;&#10;    function inputevents(e)&#10;        if (e.type == IEVENT_LMOUSEDOWN) then&#10;            for _, Section in ipairs(HUD_Sections) do&#10;                if (e.elementid == Section.StateSwitch) then&#10;                    Section.State = not Section.State&#10;                    return&#10;                end&#10;            end&#10;        for _, Section in ipairs(HUD_Sections) do&#10;                if (Section.Name == 'ENGINE STATES') then&#10;                    for _, SectionItem in ipairs(Section.Items) do&#10;                        if (e.elementid == SectionItem[4]) then&#10;                            SectionItem[3]()&#10;                            return&#10;                        end&#10;                    end&#10;                end&#10;            end&#10;        end&#10;&#10;        if (e.type == IEVENT_MMOUSEDOWN) then&#10;            Moving, Temp = true, {$cursor.x - Moved[1], $cursor.y - Moved[2]}&#10;        end&#10;&#10;        if (e.type == IEVENT_MMOUSEUP) then&#10;            Moving = false&#10;        end&#10;    end&#10;    &#10;    setmaskcolorxp(0)&#10;init end&#10;&#10;if (Moving) then&#10;    auto(10)&#10;    Moved = {$cursor.x - Temp[1], $cursor.y - Temp[2]}&#10;end&#10;&#10;setposition($clientwin.left + 5 + Moved[1], $worldwin.top + Moved[2])&#10;setfontstyle('Tahoma', 8, 75, 0xFFFFFF, 1, color(0, 0, 0, 20))&#10;&#10;local YPosition, SectionRow, SectionItemsRow = 0, 0, 0&#10;&#10;if MMS.ShowInfo then&#10;    local StringWidth, StringHeight = measurestring('TEMP')&#10;&#10;    setfillstyle('gradient', 'linear', 2, 0, 0, 0, 22)&#10;    addgradcolors(unpack(HUD_Colors.SectionHeaderBackground))&#10;    drawroundrect(0, 0, 240, 21, 2, 2)&#10;    drawtext(MMS.Title, 6, 21 / 2 - StringHeight * 0.5)&#10;&#10;    setfillstyle('gradient', 'linear', 2, 0, 0, 0, 22)&#10;    addgradcolors(unpack(HUD_Colors.EntryValueBackground))&#10;    drawroundrect(130, 0, 110, 21, 2, 2)&#10;    drawtext(MMS.Creator, 136, 21 / 2 - StringHeight * 0.5)&#10;&#10;    setfontsize(7)&#10;&#10;    local StringWidth, StringHeight = measurestring('TEMP')&#10;&#10;    setfillstyle('gradient', 'linear', 2, 0, 0, 0, 16)&#10;    addgradcolors(unpack(HUD_Colors.EntryNameBackground))&#10;    drawroundrect(0, 24 + 0 * 18, 240, 15, 2, 2)&#10;    drawtext(MMS.Info, 6, 24 + 0 * 18 + 15 / 2 - StringHeight * 0.5 + 1)&#10;     &#10;    setfillstyle('gradient', 'linear', 2, 0, 0, 0, 16)&#10;    addgradcolors(unpack(HUD_Colors.EntryNameBackground))&#10;    drawroundrect(0, 24 + 1 * 18, 240, 15, 2, 2)&#10;    drawtext('Script version:', 6, 24 + 1 * 18 + 15 / 2 - StringHeight * 0.5 + 1)&#10;     &#10;    setfillstyle('gradient', 'linear', 2, 0, 0, 0, 16)&#10;    addgradcolors(unpack(HUD_Colors.EntryValueBackground))&#10;    drawroundrect(130, 24 + 1 * 18, 110, 15, 2, 2)&#10;    drawtext(MMS.Version, 136, 24 + 1 * 18 + 15 / 2 - StringHeight * 0.5 + 1)&#10;    &#10;    YPosition = 22 + 2 * 19&#10;end&#10;&#10;for SectionIndex, Section in ipairs(HUD_Sections) do&#10;    setfontsize(8)&#10;&#10;    local StringWidth, StringHeight = measurestring('TEMP')&#10;&#10;    setfillstyle('gradient', 'linear', 2, 0, 0, 0, 21)&#10;    addgradcolors(unpack(HUD_Colors.SectionHeaderBackground))&#10;    drawroundrect(0, YPosition + (SectionRow * 23) + (SectionItemsRow * 19), 240, 20, 2, 2)&#10;    drawtext(Section.Name, 6, YPosition + (SectionRow * 23) + (SectionItemsRow * 19) + 20 / 2 - StringHeight * 0.5 + 1)&#10;&#10;    setfillstyle('gradient', 'linear', 2, 0, 0, 0, 21)&#10;    if (Section.State) then&#10;        addgradcolors(unpack(HUD_Colors.EntryValueEnabledBackground))&#10;    else&#10;        addgradcolors(unpack(HUD_Colors.EntryValueDisabledBackground))&#10;    end&#10;    Section.StateSwitch = drawroundrect(220, YPosition + (SectionRow * 23) + (SectionItemsRow * 19), 20, 20, 2, 2)&#10;    drawtext('X', 228, YPosition + (SectionRow * 23) + (SectionItemsRow * 19) + 20 / 2 - StringHeight * 0.5 + 1)&#10;&#10;    SectionRow = SectionRow + 1&#10;&#10;    if (Section.State) then&#10;        setfontsize(7)&#10;&#10;        local StringWidth, StringHeight = measurestring('TEMP')&#10;&#10;        for SectionItemIndex, SectionItem in ipairs(Section.Items) do&#10;            setfillstyle('gradient', 'linear', 2, 0, 0, 0, 17)     &#10;            addgradcolors(unpack(HUD_Colors.EntryNameBackground))&#10;            drawroundrect(0, YPosition + (SectionRow * 23) + (SectionItemsRow * 19), 240, 16, 2, 2)&#10;            drawtext(SectionItem[1], 6, YPosition + (SectionRow * 23) + (SectionItemsRow * 19) + 16 / 2 - StringHeight * 0.5 + 1)&#10;&#10;            if (Section.Name == 'ENGINE STATES') then&#10;                local EngineCurrentState = SectionItem[2]()&#10;&#10;                setfillstyle('gradient', 'linear', 2, 0, 0, 0, 17)&#10;                if (EngineCurrentState == 'yes') then&#10;                    addgradcolors(unpack(HUD_Colors.EntryValueEnabledBackground))&#10;                else&#10;                    addgradcolors(unpack(HUD_Colors.EntryValueDisabledBackground))&#10;                end&#10;                HUD_Sections[SectionIndex].Items[SectionItemIndex][4] = drawroundrect(130, YPosition + (SectionRow * 23) + (SectionItemsRow * 19), 110, 16, 2, 2)&#10;&#10;&#10;                drawtext((EngineCurrentState == 'yes' and ('On')) or ('Off'), 136, YPosition + (SectionRow * 23) + (SectionItemsRow * 19) + 16 / 2 - StringHeight * 0.5 + 1)&#10;            else&#10;                setfillstyle('gradient', 'linear', 2, 0, 0, 0, 17)&#10;                addgradcolors(unpack(HUD_Colors.EntryValueBackground))&#10;                drawroundrect(130, YPosition + (SectionRow * 23) + (SectionItemsRow * 19), 110, 16, 2, 2)&#10;                drawtext(SectionItem[2](), 136, YPosition + (SectionRow * 23) + (SectionItemsRow * 19) + 16 / 2 - StringHeight * 0.5 + 1)&#10;            end&#10;&#10;            SectionItemsRow = SectionItemsRow + 1&#10;        end&#10;    end&#10;end" enabled="yes" refreshRate="100"/>
        </HUDScripts>
    </HUDs>
    <GeneralSettings>
        <Input>
            <MouseOption mouseMode="Simulate Mouse"/>
            <MouseOption scrollMode="Use mouse wheel"/>
            <MouseOption stuckCursorPolicy="If Cavebot on, Release Instantly"/>
            <MouseOption moveSpeed="9"/>
            <MouseOption clickWaitMin="30" clickWaitMax="50"/>
            <KeyboardOption keyboardMode="Simulate Keyboard"/>
            <KeyboardOption stuckCtrlShiftPolicy="If Cavebot on, Release after 1 sec"/>
            <KeyboardOption typeWaitMin="75" typeWaitMax="140"/>
            <KeyboardOption pressWaitMin="45" pressWaitMax="65"/>
            <FocusOption focusPolicy="Don't auto-focus"/>
            <FocusOption openMenuPolicy="Confirm if cavebotting"/>
        </Input>
    </GeneralSettings>
    <Alerts disableSounds="no">
        <alert name="Player On Screen" playSound="no" pauseBot="no" logout="no" safeList="&lt;SafeList&gt;&#10;"/>
        <alert name="Player Attacking" playSound="yes" pauseBot="no" logout="no" safeList="&lt;SafeList&gt;&#10;"/>
        <alert name="Monster Attacking" playSound="no" pauseBot="no" logout="no" safeList="&lt;SafeList&gt;&#10;"/>
        <alert name="Private Message" playSound="no" pauseBot="no" logout="no" safeList="&lt;SafeList&gt;&#10;"/>
        <alert name="Default Message" playSound="no" pauseBot="no" logout="no" safeList="&lt;SafeList&gt;&#10;"/>
        <alert name="GM Detected" playSound="no" pauseBot="no" logout="no"/>
        <alert name="Disconnected" playSound="yes" pauseBot="no" logout="no"/>
        <alert name="Character Stuck" playSound="no" pauseBot="no" logout="no" standTime="30000"/>
        <alert name="Health Below" playSound="no" pauseBot="no" logout="no" healthPercent="50"/>
        <alert name="Mana Below" playSound="no" pauseBot="no" logout="no" manaPercent="50"/>
        <alert name="Unjust Kill" playSound="no" pauseBot="no" logout="no"/>
        <alert name="Enemies Online" playSound="no" pauseBot="no" logout="no" enemiesCount="50"/>
    </Alerts>
    <Cavebot enabled="no">
        <Options>
            <Option shovel="3457"/>
            <Option rope="3003"/>
            <Option machete="3308"/>
            <Option pick="3456"/>
            <Option nodeRange="4"/>
            <Option pauseBotOnDeath="yes"/>
            <Option refillAmmo="no" refillAmmoMin="30" refillAmmoMax="70"/>
            <Option autoMount="no"/>
            <Option fireAvoidanceMin="0" fireAvoidanceMax="0"/>
            <Option energyAvoidanceMin="0" energyAvoidanceMax="0"/>
            <Option poisonAvoidanceMin="0" poisonAvoidanceMax="0"/>
            <Option walkThroughPlayers="yes"/>
            <Option walkMethod="Walk With Arrow Keys"/>
            <Option walkableItems="140, 404, 831, 832, 833, 834, 883, 2118, 2119, 2120, 2121, 2122, 2123, 2124, 2125, 2126, 2127, 2131, 2132, 2133, 2134, 2135, 2314, 2315, 2316, 2319, 2346, 2347, 2348, 2349, 2350, 2351, 2352, 2353, 2354, 2355, 2356, 2357, 2358, 2359, 2360, 2361, 2362, 2363, 2364, 2365, 2366, 2367, 2368, 2369, 2370, 2371, 2372, 2373, 2374, 2375, 2376, 2377, 2378, 2379, 2380, 2381, 2382, 2383, 2384, 2385, 2418, 2419, 2420, 2421, 2422, 2423, 2424, 2425, 2426, 2431, 2432, 2433, 2434, 2441, 2442, 2443, 2444, 2469, 2471, 2472, 2473, 2478, 2480, 2481, 2482, 2483, 2484, 2485, 2486, 2519, 2523, 2775, 2776, 2777, 2778, 2779, 2780, 2781, 2782, 2783, 2784, 2785, 2786, 2787, 2788, 2789, 2790, 2791, 2792, 2793, 2794, 2795, 2796, 2797, 2798, 2799, 2800, 2801, 2802, 2803, 2804, 2805, 2806, 2807, 2808, 2809, 2810, 2811, 2812, 2981, 2982, 2983, 2984, 2985, 2987, 2988, 3503, 3504, 3514, 3807, 5086, 5087, 5088, 6114, 6115, 6355, 6356, 6357, 6358, 6359, 6360, 6361, 6362, 6371, 6372, 7864, 8455, 8763, 9061, 9062, 10207, 10209, 10216, 10286, 10287, 10288, 11009, 11800, 11801, 11802, 11803, 11804, 11805, 11806, 11807, 11808, 11809, 11810"/>
            <Option mapWalkDistMin="20" mapWalkDistMax="50"/>
            <Option userOptionsScript="{&#10; &#9;&quot;type&quot;  : &quot;group&quot;,&#10; &#9;&quot;name&quot;  : &quot;Backpack Setup&quot;,&#10;&#9;&quot;column&quot; : 2,&#10; &#9;&quot;children&quot; : &#10;&#9;&#9;[&#10;       &#9;&#9;{&#10;  &#9;&#9;&#9;&#9;&quot;type&quot; : &quot;lineedit&quot;,&#10;  &#9;&#9;&#9;&#9;&quot;name&quot; : &quot;MainBP&quot;,&#10;&#9;&#9;&#9;&#9;&quot;description&quot; : &quot;&lt;p&gt;&lt;strong&gt;Main Backpack&lt;/strong&gt;&lt;br&gt;Name of your main backpack.&lt;/p&gt;&quot;,&#10;  &#9;&#9;&#9;&#9;&quot;text&quot; : &quot;Main Backpack Name&quot;,&#10;&#9;&#9;&#9;&#9;&quot;value&quot; : &quot;Blue Backpack&quot;&#10;  &#9;&#9;&#9;},&#10;&#9;&#9;&#9;{&#10;  &#9;&#9;&#9;&#9;&quot;type&quot; : &quot;lineedit&quot;,&#10;  &#9;&#9;&#9;&#9;&quot;name&quot; : &quot;LootBP&quot;,&#10;&#9;&#9;&#9;&#9;&quot;description&quot; : &quot;&lt;p&gt;&lt;strong&gt;Loot Backpack&lt;/strong&gt;&lt;br&gt;Name of yours loot backpacks.&lt;/p&gt;&quot;,&#10;  &#9;&#9;&#9;&#9;&quot;text&quot; : &quot;Loot Backpack Name&quot;,&#10;&#9;&#9;&#9;&#9;&quot;value&quot; : &quot;Camouflage Backpack&quot;&#10;&#9;&#9;&#9;},&#10;&#9;&#9;&#9;{&#10;  &#9;&#9;&#9;&#9;&quot;type&quot; : &quot;lineedit&quot;,&#10;  &#9;&#9;&#9;&#9;&quot;name&quot; : &quot;GoldBP&quot;,&#10;&#9;&#9;&#9;&#9;&quot;description&quot; : &quot;&lt;p&gt;&lt;strong&gt;Gold Backpack&lt;/strong&gt;&lt;br&gt;Name of yours gold backpacks.&lt;/p&gt;&quot;,&#10;  &#9;&#9;&#9;&#9;&quot;text&quot; : &quot;Gold Backpack Name&quot;, &#10;&#9;&#9;&#9;&#9;&quot;value&quot; : &quot;Beach Backpack&quot;&#10;&#9;&#9;&#9;}&#10;&#10;     &#9;]&#10;},&#10;{&#10; &#9;&quot;type&quot;  : &quot;group&quot;,&#10; &#9;&quot;name&quot;  : &quot;Depot Backpack Setup&quot;,&#10;&#9;&quot;column&quot; : 2,&#10; &#9;&quot;children&quot; : &#10;&#9;[&#10;       &#9;{&#10;  &#9;&#9;&#9;&quot;type&quot; : &quot;lineedit&quot;,&#10;  &#9;&#9;&#9;&quot;name&quot; : &quot;MainDPBP&quot;,&#10;&#9;&#9;&#9;&quot;description&quot; : &quot;&lt;p&gt;&lt;strong&gt;Main Depot Backpack&lt;/strong&gt;&lt;br&gt;Name of your main backpack in depot.&lt;/p&gt;&quot;,&#10;  &#9;&#9;&#9;&quot;text&quot; : &quot;Main Depot Backpack Name&quot;,&#10;&#9;&#9;&#9;&quot;value&quot; : &quot;Brown Backpack&quot;&#10;  &#9;&#9;},&#10;&#9;&#9;{&#10;  &#9;&#9;&#9;&quot;type&quot; : &quot;lineedit&quot;,&#10;  &#9;&#9;&#9;&quot;name&quot; : &quot;StackBP&quot;,&#10;&#9;&#9;&#9;&quot;description&quot; : &quot;&lt;p&gt;&lt;strong&gt;Stackables Backpack&lt;/strong&gt;&lt;br&gt;Name of yours stackable items backpacks, which are inside main depot backpack.&lt;/p&gt;&quot;,&#10;  &#9;&#9;&#9;&quot;text&quot; : &quot;Stack Bp&quot;,&#10;&#9;&#9;&#9;&quot;value&quot; : &quot;Purple Backpack&quot;&#10;  &#9;&#9;},&#10;&#9;&#9;{&#10;  &#9;&#9;&#9;&quot;type&quot; : &quot;lineedit&quot;,&#10;  &#9;&#9;&#9;&quot;name&quot; : &quot;RareBP&quot;,&#10;&#9;&#9;&#9;&quot;description&quot; : &quot;&lt;p&gt;&lt;strong&gt;Non Stackables Backpack&lt;/strong&gt;&lt;br&gt;Name of yours non stackable items backpacks, which are inside main depot backpack.&lt;/p&gt;&quot;,&#10;  &#9;&#9;&#9;&quot;text&quot; : &quot;Non Stack Bp&quot;,&#10;&#9;&#9;&#9;&quot;value&quot; : &quot;Orange Backpack&quot;&#10;  &#9;&#9;}&#10;&#9;]&#10;},&#10;{&#10; &#9;&quot;type&quot;  : &quot;group&quot;,&#10; &#9;&quot;name&quot;  : &quot;Supply List&quot;,&#10;&#9;&quot;column&quot; : 1,&#10; &#9;&quot;children&quot; : &#10;&#9;[&#10;       &#9;{&#10;  &#9;&#9;&#9;&#9;&#9;&#10;       &#9;&#9;&quot;type&quot; : &quot;spinbox&quot;,&#10;       &#9;&#9;&quot;name&quot; : &quot;MpToBuy&quot;,&#10;&#9;&#9;&#9;&quot;description&quot; : &quot;&lt;p&gt;&lt;strong&gt;Mana Potions&lt;/strong&gt;&lt;br&gt;Amount of mana potions to buy.&lt;/p&gt;&quot;,&#10;       &#9;&#9;&quot;text&quot; : &quot;Mana potions to buy: &quot;,&#10;&#9;&#9;&#9;&quot;max&quot; : 5000,&#10;       &#9;&#9;&quot;value&quot; : false&#10;&#9;},&#10;&#10;&#9;&#9;&#9;{&#10;  &#9;&#9;&#9;&quot;type&quot; : &quot;spinbox&quot;,&#10;  &#9;&#9;&#9;&quot;name&quot; : &quot;HpToBuy&quot;,&#10;&#9;&#9;&#9;&quot;description&quot; : &quot;&lt;p&gt;&lt;strong&gt;Number of Health Potion will buy&lt;/strong&gt;&lt;br&gt;Number of Health Potion will buy.&lt;/p&gt;&quot;,&#10;  &#9;&#9;&#9;&quot;text&quot; : &quot;Health Potion to buy&quot;,&#10;&#9;&#9;&#9;&quot;max&quot; : 5000,&#10;&#9;&#9;&#9;&quot;value&quot; : false&#10;&#9;},&#10;&#10;&#9;&#9;&#9;{&#10;  &#9;&#9;&#9;&quot;type&quot; : &quot;spinbox&quot;,&#10;  &#9;&#9;&#9;&quot;name&quot; : &quot;MpToLeave&quot;,&#10;&#9;&#9;&#9;&quot;description&quot; : &quot;&lt;p&gt;&lt;strong&gt;Number of Mana Potion to Leave cave&lt;/strong&gt;&lt;br&gt;Number of Mana Potion Leave.&lt;/p&gt;&quot;,&#10;  &#9;&#9;&#9;&quot;text&quot; : &quot;Mana Potion to leave&quot;,&#10;&#9;&#9;&#9;&quot;max&quot; : 5000,&#10;&#9;&#9;&#9;&quot;value&quot; : false&#10;&#9;},&#10;&#10;&#9;&#9;&#9;{&#10;  &#9;&#9;&#9;&quot;type&quot; : &quot;spinbox&quot;,&#10;  &#9;&#9;&#9;&quot;name&quot; :  &quot;HpToLeave&quot;,&#10;&#9;&#9;&#9;&quot;description&quot; : &quot;&lt;p&gt;&lt;strong&gt; HP to leave&lt;/strong&gt;&lt;br&gt;Number of Health Potion will Leave.&lt;/p&gt;&quot;,&#10;  &#9;&#9;&#9;&quot;text&quot; : &quot;Health Potion to Leave&quot;,&#10;&#9;&#9;&#9;&quot;max&quot; : 5000,&#10;&#9;&#9;&#9;&quot;value&quot; : false&#10;&#9;},&#10;&#9;&#9;&#9;{&#10;       &#9;&#9;&quot;type&quot; : &quot;spinbox&quot;,&#10;       &#9;&#9;&quot;name&quot; : &quot;CapToLeave&quot;,&#10;&#9;&#9;&#9;&quot;description&quot; : &quot;&lt;p&gt;&lt;strong&gt;Cap to leave&lt;/strong&gt;&lt;br&gt;Minimum cap to leave the spawn.&lt;/p&gt;&quot;,&#10;       &#9;&#9;&quot;text&quot; : &quot;Cap : &quot;,&#10;&#9;&#9;&#9;&quot;min&quot; : -1,&#10;&#9;&#9;&#9;&quot;suffix&quot; : &quot; oz&quot;,&#10;       &#9;&#9;&quot;value&quot; : 40&#10;      &#9;}&#10;]&#10;},&#10; &#10; {&#10; &#9;&quot;type&quot;  : &quot;group&quot;,&#10; &#9;&quot;name&quot;  : &quot;Supply Name&quot;,&#10;&#9;&quot;column&quot; : 1,&#10; &#9;&quot;children&quot; : &#10;&#9;[&#9;&#9;&#10;{&#10;  &#9;&#9;&#9;&quot;type&quot; : &quot;lineedit&quot;,&#10;  &#9;&#9;&#9;&quot;name&quot; : &quot;MPname&quot;,&#10;&#9;&#9;&#9;&quot;description&quot; : &quot;&lt;p&gt;&lt;strong&gt;Don't Edit&lt;/strong&gt;&lt;br&gt;Don't edit!&lt;/p&gt;&quot;,&#10;  &#9;&#9;&#9;&quot;text&quot; : &quot;MPname&quot;,&#10;&#9;&#9;&#9;&quot;value&quot; : &quot;Mana Potion&quot;&#10;  &#9;&#9;},&#10;&#10;&#9;&#9;&#9;{&#10;  &#9;&#9;&#9;&quot;type&quot; : &quot;lineedit&quot;,&#10;  &#9;&#9;&#9;&quot;name&quot; : &quot;HPname&quot;,&#10;&#9;&#9;&#9;&quot;description&quot; : &quot;&lt;p&gt;&lt;strong&gt;Edit like your way.&lt;/strong&gt;&lt;br&gt;Your way!&lt;/p&gt;&quot;,&#10;  &#9;&#9;&#9;&quot;text&quot; : &quot;HPname&quot;,&#10;&#9;&#9;&#9;&quot;value&quot; : &quot;Health Potion&quot;&#10;  &#9;&#9;},&#10;&#10;{&#10;  &#9;&#9;&#9;&quot;type&quot; : &quot;spinbox&quot;,&#10;  &#9;&#9;&#9;&quot;name&quot; : &quot;HPprice&quot;,&#10;&#9;&#9;&#9;&quot;description&quot; : &quot;&lt;p&gt;&lt;strong&gt;How does it cost?.&lt;/strong&gt;&lt;br&gt;How does it cost?!&lt;/p&gt;&quot;,&#10;  &#9;&#9;&#9;&quot;text&quot; : &quot;HPprice&quot;,&#10;&#9;&#9;&#9;&quot;value&quot; : false,&#10;&#9;&#9;&#9;&quot;max&quot; : 500,&#10;&#9;&#9;&#9;&quot;suffix&quot; : &quot; gold&quot;&#10;  &#9;&#9;},&#10;&#10;{&#10;  &#9;&#9;&#9;&quot;type&quot; : &quot;spinbox&quot;,&#10;  &#9;&#9;&#9;&quot;name&quot; : &quot;MPprice&quot;,&#10;&#9;&#9;&#9;&quot;description&quot; : &quot;&lt;p&gt;&lt;strong&gt;How does it cost?.&lt;/strong&gt;&lt;br&gt;How does it cost?!&lt;/p&gt;&quot;,&#10;  &#9;&#9;&#9;&quot;text&quot; : &quot;MPprice&quot;,&#10;&#9;&#9;&#9;&quot;value&quot; : false,&#10;&#9;&#9;&#9;&quot;max&quot; : 500,&#10;&#9;&#9;&#9;&quot;suffix&quot; : &quot; gold&quot;&#10;  &#9;&#9;}&#10;&#10;  &#9;&#9;]&#10;},&#10;&#10;&#9;{&#10;&#9;&quot;type&quot;  : &quot;group&quot;,&#10; &#9;&quot;name&quot;  : &quot;Hunt - Setup&quot;,&#10; &#9;&quot;children&quot; : &#10;    [&#10;&#9;&#9;{&#10;       &#9;&#9;&quot;type&quot; : &quot;checkbox&quot;,&#10;       &#9;&#9;&quot;name&quot; : &quot;DownCaveCrab&quot;,&#10;&#9;&#9;&#9;&quot;description&quot; : &quot;&lt;p&gt;&lt;strong&gt;Down Cave Check&lt;/strong&gt;&lt;br&gt;It will down cave if mark.&lt;/p&gt;&quot;,&#10;       &#9;&#9;&quot;text&quot; : &quot;DownCaveCrab&quot;,&#10;       &#9;&#9;&quot;value&quot; : true&#10;      &#9;},&#10;&#10;&#9;{&#10;       &#9;&#9;&quot;type&quot; : &quot;checkbox&quot;,&#10;       &#9;&#9;&quot;name&quot; : &quot;Down Bonelord Cave&quot;,&#10;&#9;&#9;&#9;&quot;description&quot; : &quot;&lt;p&gt;&lt;strong&gt;Down Cave Check&lt;/strong&gt;&lt;br&gt;It will down cave if mark.&lt;/p&gt;&quot;,&#10;       &#9;&#9;&quot;text&quot; : &quot;Down Bonelord Cave&quot;,&#10;       &#9;&#9;&quot;value&quot; : true&#10;      &#9;}&#10;]&#10;&#9;}"/>
        </Options>
        <SpecialAreas>
            <Area name="SArea" x="32677" y="32608" z="8" type="Square (Filled)" width="3" height="3" avoidance="250" waitTimeMin="0" waitTimeMax="0" policy="Cavebot &amp; Targeting" ignoreWhenLuring="no" ignoreWhenLooting="no" comment=""/>
        </SpecialAreas>
        <CavebotScripts/>
        <WaypointSection name="Location">
            <Waypoint type="Stand" x="32623" y="32748" z="7" rangeX="1" rangeY="1"/>
            <Waypoint type="Action" x="32623" y="32748" z="7" rangeX="1" rangeY="1" script="if islocation(15) then&#10;&#9;gotolabel(&quot;Depot&quot;, &quot;City&quot;)&#10;else&#10;&#9;gotolabel(&quot;Down&quot;, &quot;Spawn&quot;)&#10;end"/>
        </WaypointSection>
        <WaypointSection name="City">
            <Waypoint type="Stand" x="32623" y="32748" z="7" rangeX="1" rangeY="1" label="Depot"/>
            <Waypoint type="Action" x="32627" y="32751" z="7" rangeX="1" rangeY="1" script="setsetting(&quot;Alerts/PlayerOnScreen/PlaySound&quot;,&quot;no&quot;)&#10;setsetting(&quot;Persistent/Scripts/vial/Enabled&quot;, &quot;no&quot;)&#10;setsetting(&quot;Persistent/Scripts/safe bank/Enabled&quot;, &quot;yes&quot;)&#10;setsetting(&quot;Persistent/Scripts/Eat/Enabled&quot;, &quot;no&quot;)&#10;setlooting('off')&#10;settargeting('on')&#10;setsetting('Looting/OpenNextBP', 'no')&#10;setsetting('Cavebot/WalkThroughPlayers', 'yes')&#10;setsetting(&quot;Persistent/Scripts/backpack/Enabled&quot;, &quot;yes&quot;)&#10;setsetting(&quot;Persistent/Scripts/AttackCreature/Enabled&quot;, &quot;yes&quot;)"/>
            <Waypoint type="Action" x="32625" y="32747" z="7" rangeX="1" rangeY="1" label="backp" script="closewindows()&#10;wait(1000)&#10;openitem(MainBP, 'back')&#10;wait(1000)&#10;openitem(getuseroption('LootBP'), MainBP, true)&#10;wait(1000)&#10;resizewindows()&#10;wait(1000)&#10;"/>
            <Waypoint type="Action" x="32623" y="32748" z="7" rangeX="1" rangeY="1" script="if windowcount() &lt; 2 then gotolabel('backp') end"/>
            <Waypoint type="Stand" x="32622" y="32741" z="7" rangeX="1" rangeY="1"/>
            <Waypoint type="Action" x="32622" y="32741" z="7" rangeX="1" rangeY="1" script="depotaction('maindpbp', 'lootbp', {'a','stackdpbp', 'b', 'lootdpbp'})"/>
            <Waypoint type="Stand" x="32625" y="32749" z="7" rangeX="1" rangeY="1" label="Go Bank"/>
            <Waypoint type="Stand" x="32632" y="32739" z="6" rangeX="1" rangeY="1"/>
            <Waypoint type="Action" x="32632" y="32739" z="6" rangeX="1" rangeY="1" script="-- LOCATION&#10;&#10;if not islocation()&#10;then&#10;&#9;gotolabel(&quot;Go Bank&quot;)&#10;end"/>
            <Waypoint type="Action" x="32632" y="32739" z="6" rangeX="1" rangeY="1" script="-- BANK&#10;&#10;depositall_ib()&#10;wait(1000,1500)&#10;&#10;local mana = positive(MPtobuy - itemcount(getuseroption('MPname'), 'all')) * getuseroption('MPprice')&#10;local heal = positive(HPtobuy - itemcount(getuseroption('HPname'), 'all')) * getuseroption('HPprice')&#10;local Total = mana + heal + 500&#10;&#10;wait(300)&#10;npcsay(&quot;withdraw &quot;..Total)&#10;wait(300)&#10;npcsay(&quot;yes&quot;)&#10;wait(300)&#10;npcsay(&quot;balance&quot;)&#10;wait(300)"/>
            <Waypoint type="Stand" x="32627" y="32742" z="6" rangeX="1" rangeY="1" label="Go mana"/>
            <Waypoint type="Stand" x="32621" y="32742" z="5" rangeX="1" rangeY="1"/>
            <Waypoint type="Ladder" x="32626" y="32742" z="6" rangeX="1" rangeY="1"/>
            <Waypoint type="Stand" x="32622" y="32742" z="5" rangeX="1" rangeY="1"/>
            <Waypoint type="Action" x="32622" y="32742" z="5" rangeX="1" rangeY="1" script="-- LOCATION&#10;&#10;if not islocation()&#10;then&#10;&#9;gotolabel(&quot;Go Mana&quot;)&#10;end"/>
            <Waypoint type="Action" x="32622" y="32742" z="5" rangeX="1" rangeY="1" label="b" script="closewindows()&#10;wait(200)&#10;openitem(MainBP, 'back')&#10;wait(200)&#10;openitem(SupplyBP, MainBP, true)&#10;wait(500)&#10;"/>
            <Waypoint type="Action" x="32622" y="32742" z="5" rangeX="1" rangeY="1" script="if windowcount() &lt; 2 then gotolabel('b')&#10;end"/>
            <Waypoint type="Action" x="32622" y="32742" z="5" rangeX="1" rangeY="1" script="sellflasks()&#10;wait(500)&#10;&#10;local HP = getuseroption('HpToBuy')&#10;local MP = getuseroption('MpToBuy')&#10;local MPtobuy = getuseroption('MpToBuy')&#10;local HPtobuy = getuseroption('HpToBuy')&#10;&#10;buyitemsupto('mana potion', MPtobuy)&#10;wait(900)&#10;buyitemsupto('health potion', HPtobuy)&#10;wait(200)"/>
            <Waypoint type="Stand" x="32626" y="32742" z="5" rangeX="1" rangeY="1" label="Go Main Floor"/>
            <Waypoint type="Stand" x="32625" y="32749" z="6" rangeX="1" rangeY="1"/>
            <Waypoint type="Stand" x="32627" y="32751" z="7" rangeX="1" rangeY="1"/>
            <Waypoint type="Action" x="32627" y="32751" z="7" rangeX="1" rangeY="1" script="if islocation(15) then&#10;&#9;gotolabel('go hunt', &quot;Way To Hunt&quot;)&#10;else&#10;&#9;gotolabel('Go Main Floor', &quot;City&quot;)&#10;end"/>
        </WaypointSection>
        <WaypointSection name="Way To Hunt">
            <Waypoint type="Node" x="32627" y="32751" z="7" rangeX="1" rangeY="1" label="go hunt"/>
            <Waypoint type="Action" x="32627" y="32751" z="7" rangeX="1" rangeY="1" label="bb" script="closewindows()&#10;wait(600,900)&#10;openitem(MainBP, 'back')&#10;wait(1000,2000)&#10;openitem(getuseroption('LootBP'), MainBP, true)&#10;wait(1000,2000)&#10;openitem(getuseroption('GoldBP'), MainBP, true)&#10;wait(1000,2000)&#10;resizewindows()&#10;wait(600,1000)&#10;&#10;setsetting('Targeting/Creatures/Swamp Troll/Setting1/OnlyIfTrapped', 'yes')&#10;setsetting('Targeting/Creatures/Skeleton/Setting1/OnlyIfTrapped', 'yes')&#10;setsetting('Targeting/Creatures/Poison Spider/Setting1/OnlyIfTrapped', 'yes')&#10;setsetting('Targeting/Creatures/Cave Rat/Setting1/OnlyIfTrapped', 'yes')"/>
            <Waypoint type="Action" x="32675" y="32679" z="9" rangeX="1" rangeY="1" script="if windowcount() &lt; 3 then gotolabel('bb')&#10;end"/>
            <Waypoint type="Node" x="32639" y="32754" z="7" rangeX="1" rangeY="1" label="go cave"/>
            <Waypoint type="Node" x="32659" y="32745" z="7" rangeX="1" rangeY="1"/>
            <Waypoint type="Stand" x="32662" y="32741" z="7" rangeX="1" rangeY="1"/>
            <Waypoint type="Node" x="32656" y="32739" z="8" rangeX="1" rangeY="1"/>
            <Waypoint type="Node" x="32651" y="32723" z="8" rangeX="1" rangeY="1"/>
            <Waypoint type="Node" x="32658" y="32710" z="8" rangeX="1" rangeY="1"/>
            <Waypoint type="Stand" x="32654" y="32706" z="8" rangeX="1" rangeY="1"/>
            <Waypoint type="Stand" x="32659" y="32703" z="9" rangeX="1" rangeY="1"/>
            <Waypoint type="Action" x="32659" y="32703" z="9" rangeX="1" rangeY="1" script="if not islocation()&#10;then&#10;&#9;gotolabel(&quot;go cave&quot;)&#10;end&#10;"/>
            <Waypoint type="Node" x="32659" y="32700" z="9" rangeX="1" rangeY="1" label="go main cave"/>
            <Waypoint type="Node" x="32666" y="32679" z="9" rangeX="1" rangeY="1"/>
            <Waypoint type="Stand" x="32672" y="32677" z="9" rangeX="1" rangeY="1"/>
            <Waypoint type="Action" x="32671" y="32678" z="10" rangeX="1" rangeY="1" script="setsetting('Targeting/Creatures/Swamp Troll/Setting1/OnlyIfTrapped', 'no')&#10;setsetting('Targeting/Creatures/Skeleton/Setting1/OnlyIfTrapped', 'no')&#10;setsetting('Targeting/Creatures/Poison Spider/Setting1/OnlyIfTrapped', 'no')&#10;setsetting('Targeting/Creatures/Cave Rat/Setting1/OnlyIfTrapped', 'no')&#10;&#10;&#10;&#10;&#10;setsetting(&quot;Alerts/PlayerOnScreen/PlaySound&quot;,&quot;no&quot;)&#10;setsetting(&quot;Persistent/Scripts/vial/Enabled&quot;, &quot;yes&quot;)&#10;setsetting(&quot;Persistent/Scripts/safe bank/Enabled&quot;, &quot;yes&quot;)&#10;setsetting(&quot;Persistent/Scripts/Eat/Enabled&quot;, &quot;yes&quot;)&#10;setlooting('on')&#10;settargeting('on')&#10;setsetting('Looting/OpenNextBP', 'yes')&#10;setsetting('Cavebot/WalkThroughPlayers', 'yes')&#10;setsetting(&quot;Persistent/Scripts/backpack/Enabled&quot;, &quot;yes&quot;)&#10;setsetting(&quot;Persistent/Scripts/AttackCreature/Enabled&quot;, &quot;yes&quot;)"/>
            <Waypoint type="Stand" x="32671" y="32680" z="10" rangeX="1" rangeY="1"/>
            <Waypoint type="Action" x="32671" y="32680" z="10" rangeX="1" rangeY="1" script="if islocation(15) then&#10;&#9;gotolabel('Start Hunt', &quot;Spawn&quot;)&#10;else&#10;&#9;gotolabel('go main cave', &quot;Way To Hunt&quot;)&#10;end"/>
        </WaypointSection>
        <WaypointSection name="Spawn">
            <Waypoint type="Node" x="32670" y="32677" z="10" rangeX="1" rangeY="1" label="Start Hunt"/>
            <Waypoint type="Node" x="32656" y="32677" z="10" rangeX="1" rangeY="1"/>
            <Waypoint type="Node" x="32673" y="32670" z="10" rangeX="1" rangeY="1"/>
            <Waypoint type="Node" x="32682" y="32643" z="10" rangeX="1" rangeY="1"/>
            <Waypoint type="Action" x="32682" y="32643" z="10" rangeX="1" rangeY="1" label="cHeck 1" script="local MPotion = getuseroption('MPname')&#10;local MPleave = getuseroption('MpToLeave')&#10;local HPotion = getuseroption('HPname')&#10;local HPleave = getuseroption('HpToLeave')&#10;local cap = getuseroption('CapToLeave')&#10;&#10;if itemcount(MPotion) &lt;= MPleave&#10;or itemcount(HPotion) &lt;= HPleave&#10;or $cap &lt; cap&#10;or itemcount('medicine pouch') &gt;= 15&#10;then&#10;gotolabel('Refill')&#10;else&#10;gotolabel('pi')&#10;end"/>
            <Waypoint type="Stand" x="32684" y="32638" z="10" rangeX="1" rangeY="1" label="pi"/>
            <Waypoint type="Rope" x="32684" y="32639" z="10" rangeX="1" rangeY="1"/>
            <Waypoint type="Node" x="32693" y="32644" z="9" rangeX="1" rangeY="1"/>
            <Waypoint type="Node" x="32680" y="32632" z="9" rangeX="1" rangeY="1"/>
            <Waypoint type="Node" x="32669" y="32616" z="9" rangeX="1" rangeY="1"/>
            <Waypoint type="Action" x="32664" y="32615" z="9" rangeX="1" rangeY="1" script="if getuseroption(&quot;DownCaveCrab&quot;) then&#10;gotolabel(&quot;Down Cave&quot;)&#10;else gotolabel(&quot;Skip Crab&quot;)&#10;end"/>
            <Waypoint type="Stand" x="32664" y="32613" z="9" rangeX="1" rangeY="1" label="Down Cave"/>
            <Waypoint type="Node" x="32658" y="32605" z="10" rangeX="1" rangeY="1"/>
            <Waypoint type="Stand" x="32664" y="32612" z="10" rangeX="1" rangeY="1"/>
            <Waypoint type="Rope" x="32664" y="32613" z="10" rangeX="1" rangeY="1"/>
            <Waypoint type="Node" x="32672" y="32617" z="9" rangeX="1" rangeY="1" label="Skip Crab"/>
            <Waypoint type="Node" x="32683" y="32604" z="9" rangeX="1" rangeY="1"/>
            <Waypoint type="Stand" x="32691" y="32588" z="9" rangeX="1" rangeY="1"/>
            <Waypoint type="Rope" x="32691" y="32589" z="9" rangeX="1" rangeY="1"/>
            <Waypoint type="Node" x="32687" y="32605" z="8" rangeX="1" rangeY="1"/>
            <Waypoint type="Node" x="32685" y="32622" z="8" rangeX="1" rangeY="1"/>
            <Waypoint type="Node" x="32672" y="32590" z="8" rangeX="1" rangeY="1"/>
            <Waypoint type="Node" x="32694" y="32585" z="8" rangeX="1" rangeY="1"/>
            <Waypoint type="Node" x="32694" y="32576" z="8" rangeX="1" rangeY="1"/>
            <Waypoint type="Node" x="32700" y="32595" z="8" rangeX="1" rangeY="1"/>
            <Waypoint type="Node" x="32691" y="32593" z="8" rangeX="1" rangeY="1"/>
            <Waypoint type="Stand" x="32691" y="32589" z="8" rangeX="1" rangeY="1"/>
            <Waypoint type="Node" x="32694" y="32594" z="9" rangeX="1" rangeY="1"/>
            <Waypoint type="Node" x="32706" y="32612" z="9" rangeX="1" rangeY="1"/>
            <Waypoint type="Node" x="32708" y="32631" z="9" rangeX="1" rangeY="1"/>
            <Waypoint type="Action" x="32708" y="32629" z="9" rangeX="1" rangeY="1" script="if getuseroption(&quot;Down Bonelord Cave&quot;) then&#10;gotolabel(&quot;Down Bonelord&quot;)&#10;else gotolabel(&quot;Skip Bonelord&quot;)&#10;end"/>
            <Waypoint type="Stand" x="32709" y="32617" z="9" rangeX="1" rangeY="1" label="Down Bonelord"/>
            <Waypoint type="Node" x="32708" y="32623" z="10" rangeX="1" rangeY="1"/>
            <Waypoint type="Node" x="32712" y="32610" z="10" rangeX="1" rangeY="1"/>
            <Waypoint type="Stand" x="32709" y="32616" z="10" rangeX="1" rangeY="1"/>
            <Waypoint type="Rope" x="32709" y="32617" z="10" rangeX="1" rangeY="1"/>
            <Waypoint type="Node" x="32706" y="32615" z="9" rangeX="1" rangeY="1" label="Skip Bonelord"/>
            <Waypoint type="Node" x="32689" y="32599" z="9" rangeX="1" rangeY="1"/>
            <Waypoint type="Node" x="32683" y="32612" z="9" rangeX="1" rangeY="1"/>
            <Waypoint type="Node" x="32681" y="32638" z="9" rangeX="1" rangeY="1"/>
            <Waypoint type="Stand" x="32684" y="32639" z="9" rangeX="1" rangeY="1"/>
            <Waypoint type="Node" x="32682" y="32652" z="10" rangeX="1" rangeY="1"/>
            <Waypoint type="Node" x="32679" y="32670" z="10" rangeX="1" rangeY="1"/>
            <Waypoint type="Action" x="32672" y="32677" z="10" rangeX="1" rangeY="1" script="local MPotion = getuseroption('MPname')&#10;local MPleave = getuseroption('MpToLeave')&#10;local HPotion = getuseroption('HPname')&#10;local HPleave = getuseroption('HpToLeave')&#10;local cap = getuseroption('CapToLeave')&#10;&#10;if itemcount(MPotion) &lt;= MPleave&#10;or itemcount(HPotion) &lt;= HPleave&#10;or $cap &lt; cap&#10;or itemcount('medicine pouch') &gt;= 15&#10;then&#10;gotolabel('Refill')&#10;else&#10;gotolabel('Start Hunt')&#10;end"/>
            <Waypoint type="Stand" x="32672" y="32676" z="10" rangeX="1" rangeY="1" label="Refill"/>
            <Waypoint type="Action" x="32672" y="32678" z="10" rangeX="1" rangeY="1" script="setsetting('Targeting/Creatures/Swamp Troll/Setting1/OnlyIfTrapped', 'yes')&#10;setsetting('Targeting/Creatures/Skeleton/Setting1/OnlyIfTrapped', 'yes')&#10;setsetting('Targeting/Creatures/Poison Spider/Setting1/OnlyIfTrapped', 'yes')&#10;setsetting('Targeting/Creatures/Cave Rat/Setting1/OnlyIfTrapped', 'yes')&#10;setsetting('Targeting/Creatures/Bug/Setting1/OnlyIfTrapped', 'yes')&#10;&#10;&#10;&#10;&#10;&#10;setsetting(&quot;Alerts/PlayerOnScreen/PlaySound&quot;,&quot;no&quot;)&#10;setsetting(&quot;Persistent/Scripts/vial/Enabled&quot;, &quot;no&quot;)&#10;setsetting(&quot;Persistent/Scripts/safe bank/Enabled&quot;, &quot;yes&quot;)&#10;setsetting(&quot;Persistent/Scripts/Eat/Enabled&quot;, &quot;no&quot;)&#10;setlooting('off')&#10;settargeting('on')&#10;setsetting('Looting/OpenNextBP', 'yes')&#10;setsetting('Cavebot/WalkThroughPlayers', 'yes')&#10;setsetting(&quot;Persistent/Scripts/backpack/Enabled&quot;, &quot;yes&quot;)&#10;setsetting(&quot;Persistent/Scripts/AttackCreature/Enabled&quot;, &quot;yes&quot;)"/>
            <Waypoint type="Rope" x="32672" y="32677" z="10" rangeX="1" rangeY="1"/>
            <Waypoint type="Stand" x="32675" y="32679" z="9" rangeX="1" rangeY="1"/>
            <Waypoint type="Action" x="32675" y="32679" z="9" rangeX="1" rangeY="1" script="if islocation(15) then&#10;&#9;gotolabel('Back City', &quot;Go City&quot;)&#10;else&#10;&#9;gotolabel('Refill', &quot;Spawn&quot;)&#10;end"/>
        </WaypointSection>
        <WaypointSection name="Go City">
            <Waypoint type="Node" x="32673" y="32683" z="9" rangeX="1" rangeY="1" label="Back City"/>
            <Waypoint type="Node" x="32663" y="32696" z="9" rangeX="1" rangeY="1"/>
            <Waypoint type="Node" x="32655" y="32703" z="9" rangeX="1" rangeY="1"/>
            <Waypoint type="Stand" x="32654" y="32705" z="9" rangeX="1" rangeY="1"/>
            <Waypoint type="Rope" x="32654" y="32706" z="9" rangeX="1" rangeY="1"/>
            <Waypoint type="Node" x="32655" y="32714" z="8" rangeX="1" rangeY="1"/>
            <Waypoint type="Node" x="32663" y="32727" z="8" rangeX="1" rangeY="1"/>
            <Waypoint type="Node" x="32664" y="32737" z="8" rangeX="1" rangeY="1"/>
            <Waypoint type="Stand" x="32663" y="32741" z="8" rangeX="1" rangeY="1"/>
            <Waypoint type="Rope" x="32662" y="32741" z="8" rangeX="1" rangeY="1"/>
            <Waypoint type="Stand" x="32661" y="32744" z="7" rangeX="1" rangeY="1"/>
            <Waypoint type="Action" x="32661" y="32744" z="7" rangeX="1" rangeY="1" script="-- LOCATION&#10;&#10;if not islocation()&#10;then&#10;&#9;gotolabel(&quot;Back City&quot;)&#10;end"/>
            <Waypoint type="Node" x="32658" y="32748" z="7" rangeX="1" rangeY="1" label="s"/>
            <Waypoint type="Node" x="32635" y="32752" z="7" rangeX="1" rangeY="1"/>
            <Waypoint type="Stand" x="32623" y="32750" z="7" rangeX="1" rangeY="1"/>
            <Waypoint type="Action" x="32623" y="32750" z="7" rangeX="1" rangeY="1" script="if islocation(15) then&#10;&#9;gotolabel('Depot', &quot;City&quot;)&#10;else&#10;&#9;gotolabel('11', &quot;Back City&quot;)&#10;end"/>
        </WaypointSection>
    </Cavebot>
    <Looting enabled="no">
        <Options>
            <Option range="50"/>
            <Option moveItemsQuickly="yes"/>
            <Option eatFoodFromCorpse="yes"/>
            <Option openNextBP="yes"/>
            <Option openBPsAtLogin="no"/>
            <Option valuableBodies="3000"/>
            <Option ultraValuableBodies="50000"/>
            <Option alertOnValuableBodies="no"/>
            <Option openValuableBodiesOnly="no"/>
            <Option openUltraValuableBodiesImmediately="no"/>
            <Option policy="Smart Looting"/>
            <LootingDestinations>
                <lootingDestination name="mainbp" destination="brown backpack"/>
                <lootingDestination name="lootbp" destination="golden backpack"/>
                <lootingDestination name="goldbp" destination="yellow backpack"/>
                <lootingDestination name="maindpbp" destination="fur backpack"/>
                <lootingDestination name="stackdpbp" destination="camouflage backpack"/>
                <lootingDestination name="lootdpbp" destination="camouflage backpack"/>
                <lootingDestination name="supplybp" destination="fur backpack"/>
            </LootingDestinations>
        </Options>
        <LootingProfile name="LootList" isCurrentProfile="yes">
            <LootItem name="gold coin" id="3031" sellPrice="1" weight="0.10" destinationName="goldbp" action="Loot" lootCondition="Has Cap to Loot" itemCategory="c" alertOnDrop="no" alertOnMiss="no"/>
            <LootItem name="pelvis bone" id="11481" sellPrice="30" weight="1.30" destinationName="lootbp" action="Loot" lootCondition="Has Cap to Loot" itemCategory="a" alertOnDrop="no" alertOnMiss="no"/>
            <LootItem name="swamp grass" id="9686" sellPrice="20" weight="0.94" destinationName="lootbp" action="Loot" lootCondition="Has Cap to Loot" itemCategory="a" alertOnDrop="no" alertOnMiss="no"/>
            <LootItem name="wood" id="5901" sellPrice="50" weight="5.00" destination="" action="Ignore" lootCondition="Has Cap to Loot" itemCategory="a" alertOnDrop="no" alertOnMiss="no"/>
            <LootItem name="medicine pouch" id="12517" sellPrice="0" weight="12.00" destinationName="lootbp" action="Loot" lootCondition="Has Cap to Loot" itemCategory="b" alertOnDrop="no" alertOnMiss="no"/>
            <LootItem name="small flask of eyedrops" id="11512" sellPrice="95" weight="0.50" destinationName="lootbp" action="Loot" lootCondition="Has Cap to Loot" itemCategory="a" alertOnDrop="no" alertOnMiss="no"/>
            <LootItem name="terra rod" id="3065" sellPrice="2000" weight="25.00" destinationName="lootbp" action="Loot" lootCondition="Has Cap to Loot" itemCategory="b" alertOnDrop="no" alertOnMiss="no"/>
            <LootItem name="bonelord shield" id="3418" sellPrice="1200" weight="47.00" destinationName="lootbp" action="Loot" lootCondition="Has Cap to Loot" itemCategory="b" alertOnDrop="no" alertOnMiss="no"/>
            <LootItem name="bonelord eye" id="5898" sellPrice="80" weight="5.00" destinationName="lootbp" action="Loot" lootCondition="Has Cap to Loot" itemCategory="a" alertOnDrop="no" alertOnMiss="no"/>
        </LootingProfile>
    </Looting>
    <Supplies>
        <Options>
            <Option defaultBackpack=""/>
            <Option extraCashMin="1000" extraCashMax="2500"/>
            <Option autoSwitchProfiles="no"/>
        </Options>
        <SupplyProfile name="SupplyList" vocation="Knight, Paladin, Sorcerer, Druid" level="0" isCurrentProfile="yes">
            <SupplyItem name="mana potion" id="268" buyPrice="50" weight="2.70" leaveCaveAt="0" rule="Up to..." ruleValue="0" destinationName="mainbp" category=""/>
            <SupplyItem name="great health potion" id="239" buyPrice="190" weight="3.10" leaveCaveAt="0" rule="Up to..." ruleValue="0" destinationName="mainbp" category=""/>
            <SupplyItem name="ultimate health potion" id="7643" buyPrice="310" weight="3.10" leaveCaveAt="0" rule="Up to..." ruleValue="0" destinationName="mainbp" category=""/>
            <SupplyItem name="strong health potion" id="236" buyPrice="100" weight="2.90" leaveCaveAt="0" rule="Up to..." ruleValue="0" destinationName="mainbp" category=""/>
            <SupplyItem name="great mana potion" id="238" buyPrice="120" weight="3.10" leaveCaveAt="0" rule="Up to..." ruleValue="0" destinationName="mainbp" category=""/>
            <SupplyItem name="strong mana potion" id="237" buyPrice="80" weight="2.90" leaveCaveAt="0" rule="Up to..." ruleValue="0" destinationName="mainbp" category=""/>
        </SupplyProfile>
    </Supplies>
    <Targeting enabled="yes" allowDiagonalMovement="yes" autoSwitchProfiles="no" nonPvPMode="no">
        <TargetingProfile name="TargetList" vocation="Knight, Paladin, Sorcerer, Druid" level="0" targetMustBeShootable="no" targetMustBeReachable="yes" isCurrentProfile="yes">
            <Priorities>
                <Priority health="20"/>
                <Priority proximity="30"/>
                <Priority danger="10"/>
                <Priority random="0"/>
                <Priority lure="30"/>
                <Priority stick="2"/>
            </Priorities>
            <Creatures>
                <Creature name="Swamp Troll" amount="Any" category="" dontLoot="no" playAlarm="no" syncSpells="no">
                    <FightingSettings>
                        <Setting index="0" hpFrom="0" hpTo="100" danger="0" onlyIfTrapped="no" mustAttackMe="no" action="Attack" avoidance="No Avoidance" desiredStance="Reach" distance="3" attackMode="No Change" firstSpell="" secondSpell="" thirdSpell="" fourthSpell="" spamMin="300" spamMax="500"/>
                        <Setting index="1" hpFrom="0" hpTo="0" danger="0" onlyIfTrapped="no" mustAttackMe="no" action="Attack" avoidance="No Avoidance" desiredStance="No Movement" distance="3" attackMode="No Change" firstSpell="" secondSpell="" thirdSpell="" fourthSpell="" spamMin="300" spamMax="500"/>
                        <Setting index="2" hpFrom="0" hpTo="0" danger="0" onlyIfTrapped="no" mustAttackMe="no" action="Attack" avoidance="No Avoidance" desiredStance="No Movement" distance="3" attackMode="No Change" firstSpell="" secondSpell="" thirdSpell="" fourthSpell="" spamMin="300" spamMax="500"/>
                        <Setting index="3" hpFrom="0" hpTo="0" danger="0" onlyIfTrapped="no" mustAttackMe="no" action="Attack" avoidance="No Avoidance" desiredStance="No Movement" distance="3" attackMode="No Change" firstSpell="" secondSpell="" thirdSpell="" fourthSpell="" spamMin="300" spamMax="500"/>
                    </FightingSettings>
                </Creature>
                <Creature name="Bug" amount="Any" category="" dontLoot="no" playAlarm="no" syncSpells="no">
                    <FightingSettings>
                        <Setting index="0" hpFrom="0" hpTo="100" danger="0" onlyIfTrapped="no" mustAttackMe="no" action="Attack" avoidance="No Avoidance" desiredStance="Reach" distance="3" attackMode="No Change" firstSpell="" secondSpell="" thirdSpell="" fourthSpell="" spamMin="300" spamMax="500"/>
                        <Setting index="1" hpFrom="0" hpTo="0" danger="0" onlyIfTrapped="no" mustAttackMe="no" action="Attack" avoidance="No Avoidance" desiredStance="No Movement" distance="3" attackMode="No Change" firstSpell="" secondSpell="" thirdSpell="" fourthSpell="" spamMin="300" spamMax="500"/>
                        <Setting index="2" hpFrom="0" hpTo="0" danger="0" onlyIfTrapped="no" mustAttackMe="no" action="Attack" avoidance="No Avoidance" desiredStance="No Movement" distance="3" attackMode="No Change" firstSpell="" secondSpell="" thirdSpell="" fourthSpell="" spamMin="300" spamMax="500"/>
                        <Setting index="3" hpFrom="0" hpTo="0" danger="0" onlyIfTrapped="no" mustAttackMe="no" action="Attack" avoidance="No Avoidance" desiredStance="No Movement" distance="3" attackMode="No Change" firstSpell="" secondSpell="" thirdSpell="" fourthSpell="" spamMin="300" spamMax="500"/>
                    </FightingSettings>
                </Creature>
                <Creature name="Skeleton" amount="Any" category="" dontLoot="no" playAlarm="no" syncSpells="no">
                    <FightingSettings>
                        <Setting index="0" hpFrom="0" hpTo="100" danger="0" onlyIfTrapped="no" mustAttackMe="no" action="Attack" avoidance="No Avoidance" desiredStance="Reach" distance="3" attackMode="No Change" firstSpell="" secondSpell="" thirdSpell="" fourthSpell="" spamMin="300" spamMax="500"/>
                        <Setting index="1" hpFrom="0" hpTo="0" danger="0" onlyIfTrapped="no" mustAttackMe="no" action="Attack" avoidance="No Avoidance" desiredStance="No Movement" distance="3" attackMode="No Change" firstSpell="" secondSpell="" thirdSpell="" fourthSpell="" spamMin="300" spamMax="500"/>
                        <Setting index="2" hpFrom="0" hpTo="0" danger="0" onlyIfTrapped="no" mustAttackMe="no" action="Attack" avoidance="No Avoidance" desiredStance="No Movement" distance="3" attackMode="No Change" firstSpell="" secondSpell="" thirdSpell="" fourthSpell="" spamMin="300" spamMax="500"/>
                        <Setting index="3" hpFrom="0" hpTo="0" danger="0" onlyIfTrapped="no" mustAttackMe="no" action="Attack" avoidance="No Avoidance" desiredStance="No Movement" distance="3" attackMode="No Change" firstSpell="" secondSpell="" thirdSpell="" fourthSpell="" spamMin="300" spamMax="500"/>
                    </FightingSettings>
                </Creature>
                <Creature name="Poison Spider" amount="Any" category="" dontLoot="no" playAlarm="no" syncSpells="no">
                    <FightingSettings>
                        <Setting index="0" hpFrom="0" hpTo="100" danger="0" onlyIfTrapped="no" mustAttackMe="no" action="Attack" avoidance="No Avoidance" desiredStance="Reach" distance="3" attackMode="No Change" firstSpell="" secondSpell="" thirdSpell="" fourthSpell="" spamMin="300" spamMax="500"/>
                        <Setting index="1" hpFrom="0" hpTo="0" danger="0" onlyIfTrapped="no" mustAttackMe="no" action="Attack" avoidance="No Avoidance" desiredStance="No Movement" distance="3" attackMode="No Change" firstSpell="" secondSpell="" thirdSpell="" fourthSpell="" spamMin="300" spamMax="500"/>
                        <Setting index="2" hpFrom="0" hpTo="0" danger="0" onlyIfTrapped="no" mustAttackMe="no" action="Attack" avoidance="No Avoidance" desiredStance="No Movement" distance="3" attackMode="No Change" firstSpell="" secondSpell="" thirdSpell="" fourthSpell="" spamMin="300" spamMax="500"/>
                        <Setting index="3" hpFrom="0" hpTo="0" danger="0" onlyIfTrapped="no" mustAttackMe="no" action="Attack" avoidance="No Avoidance" desiredStance="No Movement" distance="3" attackMode="No Change" firstSpell="" secondSpell="" thirdSpell="" fourthSpell="" spamMin="300" spamMax="500"/>
                    </FightingSettings>
                </Creature>
                <Creature name="Cave Rat" amount="Any" category="" dontLoot="no" playAlarm="no" syncSpells="no">
                    <FightingSettings>
                        <Setting index="0" hpFrom="0" hpTo="100" danger="0" onlyIfTrapped="no" mustAttackMe="no" action="Attack" avoidance="No Avoidance" desiredStance="Reach" distance="3" attackMode="No Change" firstSpell="" secondSpell="" thirdSpell="" fourthSpell="" spamMin="300" spamMax="500"/>
                        <Setting index="1" hpFrom="0" hpTo="0" danger="0" onlyIfTrapped="no" mustAttackMe="no" action="Attack" avoidance="No Avoidance" desiredStance="No Movement" distance="3" attackMode="No Change" firstSpell="" secondSpell="" thirdSpell="" fourthSpell="" spamMin="300" spamMax="500"/>
                        <Setting index="2" hpFrom="0" hpTo="0" danger="0" onlyIfTrapped="no" mustAttackMe="no" action="Attack" avoidance="No Avoidance" desiredStance="No Movement" distance="3" attackMode="No Change" firstSpell="" secondSpell="" thirdSpell="" fourthSpell="" spamMin="300" spamMax="500"/>
                        <Setting index="3" hpFrom="0" hpTo="0" danger="0" onlyIfTrapped="no" mustAttackMe="no" action="Attack" avoidance="No Avoidance" desiredStance="No Movement" distance="3" attackMode="No Change" firstSpell="" secondSpell="" thirdSpell="" fourthSpell="" spamMin="300" spamMax="500"/>
                    </FightingSettings>
                </Creature>
                <Creature name="crab" amount="Any" category="" dontLoot="no" playAlarm="no" syncSpells="no">
                    <FightingSettings>
                        <Setting index="0" hpFrom="0" hpTo="100" danger="0" onlyIfTrapped="no" mustAttackMe="no" action="Attack" avoidance="No Avoidance" desiredStance="Reach" distance="3" attackMode="No Change" firstSpell="" secondSpell="" thirdSpell="" fourthSpell="" spamMin="300" spamMax="500"/>
                        <Setting index="1" hpFrom="0" hpTo="0" danger="0" onlyIfTrapped="no" mustAttackMe="no" action="Attack" avoidance="No Avoidance" desiredStance="No Movement" distance="3" attackMode="No Change" firstSpell="" secondSpell="" thirdSpell="" fourthSpell="" spamMin="300" spamMax="500"/>
                        <Setting index="2" hpFrom="0" hpTo="0" danger="0" onlyIfTrapped="no" mustAttackMe="no" action="Attack" avoidance="No Avoidance" desiredStance="No Movement" distance="3" attackMode="No Change" firstSpell="" secondSpell="" thirdSpell="" fourthSpell="" spamMin="300" spamMax="500"/>
                        <Setting index="3" hpFrom="0" hpTo="0" danger="0" onlyIfTrapped="no" mustAttackMe="no" action="Attack" avoidance="No Avoidance" desiredStance="No Movement" distance="3" attackMode="No Change" firstSpell="" secondSpell="" thirdSpell="" fourthSpell="" spamMin="300" spamMax="500"/>
                    </FightingSettings>
                </Creature>
                <Creature name="Bonelord" amount="Any" category="" dontLoot="no" playAlarm="no" syncSpells="no">
                    <FightingSettings>
                        <Setting index="0" hpFrom="0" hpTo="100" danger="0" onlyIfTrapped="no" mustAttackMe="no" action="Attack" avoidance="No Avoidance" desiredStance="Reach" distance="3" attackMode="No Change" firstSpell="Apprentice's Strike" secondSpell="" thirdSpell="" fourthSpell="" spamMin="300" spamMax="500"/>
                        <Setting index="1" hpFrom="0" hpTo="0" danger="0" onlyIfTrapped="no" mustAttackMe="no" action="Attack" avoidance="No Avoidance" desiredStance="No Movement" distance="3" attackMode="No Change" firstSpell="" secondSpell="" thirdSpell="" fourthSpell="" spamMin="300" spamMax="500"/>
                        <Setting index="2" hpFrom="0" hpTo="0" danger="0" onlyIfTrapped="no" mustAttackMe="no" action="Attack" avoidance="No Avoidance" desiredStance="No Movement" distance="3" attackMode="No Change" firstSpell="" secondSpell="" thirdSpell="" fourthSpell="" spamMin="300" spamMax="500"/>
                        <Setting index="3" hpFrom="0" hpTo="0" danger="0" onlyIfTrapped="no" mustAttackMe="no" action="Attack" avoidance="No Avoidance" desiredStance="No Movement" distance="3" attackMode="No Change" firstSpell="" secondSpell="" thirdSpell="" fourthSpell="" spamMin="300" spamMax="500"/>
                    </FightingSettings>
                </Creature>
            </Creatures>
        </TargetingProfile>
    </Targeting>
    <OtherBots>
        <HealingPaths>
            <entryPath from="Healer/Rules/HP" to="PotionHealer/Rules/HP"/>
            <entryPath from="Healer/Rules/MP" to="PotionHealer/Rules/MP"/>
            <entryPath from="Healer/Rules/exura" to="SpellHealer/Rules/exura"/>
            <entryPath from="Healer/Rules/Healer0" to="SpellHealer/Rules/Healer0"/>
        </HealingPaths>
        <TargetingPaths>
            <entryPath from="Targeting/Monsters/Carrion-Worm/ListSettings/Setting0" to="Targeting/Creatures/Carrion Worm/Setting1"/>
            <entryPath from="Targeting/Monsters/Rotworm/ListSettings/Setting0" to="Targeting/Creatures/Rotworm/Setting1"/>
        </TargetingPaths>
    </OtherBots>
</WindbotSettings>
